bits/__init__.py
bits/disclosure/__init__.py
bits_disclosure-1.0.10.dist-info/LICENSE.md
bits_disclosure-1.0.10.dist-info/METADATA
bits_disclosure-1.0.10.dist-info/WHEEL
bits_disclosure-1.0.10.dist-info/top_level.txt
bits_disclosure-1.0.10.dist-info/RECORD
