Metadata-Version: 2.1
Name: bits-disclosure
Version: 1.0.10
Summary: BITS Disclosure
Author: Lukas Karlsson
Author-email: karlsson@broadinstitute.org
License: Apache Software License
License-File: LICENSE.md
Requires-Dist: bits-mongo
